tests/__init__.py
tests/tests_topsis.py
topsis/__init__.py
topsis/topsis.py
topsis_shrey_102103354-0.1.0.dist-info/METADATA
topsis_shrey_102103354-0.1.0.dist-info/WHEEL
topsis_shrey_102103354-0.1.0.dist-info/entry_points.txt
topsis_shrey_102103354-0.1.0.dist-info/top_level.txt
topsis_shrey_102103354-0.1.0.dist-info/RECORD
