Metadata-Version: 2.1
Name: topsis-shrey-102103354
Version: 0.1.0
Classifier: Programming Language :: Python :: 3
Requires-Dist: pandas
Requires-Dist: numpy
